confman
