Metadata-Version: 1.1
Name: confman
Version: 0.3.1
Summary: Lazy, rootless, yet powerful config file management mostly using symlinks
Home-page: http://git.p.engu.in/laurentb/confman/
Author: Laurent Bachelier
Author-email: laurent@bachelier.name
License: UNKNOWN
Platform: UNKNOWN
Classifier: License :: OSI Approved :: MIT License
Classifier: Programming Language :: Python :: 2.7
Classifier: Programming Language :: Python :: 3.5
Classifier: Programming Language :: Python :: 3.6
Classifier: Programming Language :: Python :: 3.7
Classifier: Programming Language :: Python :: 3.8
